{
    "type": "FeatureCollection",
    "features": [
        {
            "geometry": {
                "type": "Point",
                "coordinates": [
                    11.4089721,48.1393784
                ]
            },
            "type": "Feature",
            "properties": {
                "category": "Squareville",
                "address": "Clarita-Bernhard-Straße 16", 
                "city": "München", 
                "phone": "+49 89 212310 370",
                "email": "info@staytoo.de",
                "assetid" : "63"
            }
        }
    ]
}